acs_sdk/__init__.py
acs_sdk/client/__init__.py
acs_sdk/client/client.py
acs_sdk/client/exceptions.py
acs_sdk/client/retry.py
acs_sdk/client/types.py
acs_sdk/fuse/__init__.py
acs_sdk/fuse/__main__.py
acs_sdk/fuse/buffer.py
acs_sdk/fuse/fuse_mount.py
acs_sdk/fuse/mount_utils.py
acs_sdk/fuse/utils.py
acs_sdk/internal/__init__.py
acs_sdk/internal/ca-chain.pem
acs_sdk/internal/generated/__init__.py
acs_sdk/internal/generated/client_storage_pb2.py
acs_sdk/internal/generated/client_storage_pb2_grpc.py
acs_sdk-0.4.2.dist-info/licenses/LICENSE
acs_sdk-0.4.2.dist-info/METADATA
acs_sdk-0.4.2.dist-info/WHEEL
acs_sdk-0.4.2.dist-info/top_level.txt
acs_sdk-0.4.2.dist-info/RECORD
