Metadata-Version: 2.4
Name: acs-sdk
Version: 0.4.2
Summary: Python SDK for Accelerated Cloud Storage service
Home-page: https://github.com/AcceleratedCloudStorage/acs-sdk-python
Author: AcceleratedCloudStorage
Author-email: AcceleratedCloudStorage <sales@acceleratedcloudstorage.com>
Project-URL: Homepage, https://github.com/AcceleratedCloudStorage/acs-sdk-python
Classifier: Development Status :: 4 - Beta
Classifier: Intended Audience :: Developers
Classifier: License :: OSI Approved :: Mozilla Public License 2.0 (MPL 2.0)
Classifier: Operating System :: OS Independent
Classifier: Programming Language :: Python :: 3
Classifier: Programming Language :: Python :: 3.9
Classifier: Programming Language :: Python :: 3.10
Classifier: Programming Language :: Python :: 3.11
Classifier: Programming Language :: Python :: 3.12
Classifier: Programming Language :: Python :: 3.13
Requires-Python: >=3.8
License-File: LICENSE
Requires-Dist: grpcio>=1.70.0
Requires-Dist: grpcio-tools>=1.70.0
Requires-Dist: PyYAML>=6.0.2
Requires-Dist: protobuf>=5.29.3
Requires-Dist: iniconfig>=2.0.0
Requires-Dist: pluggy>=1.5.0
Requires-Dist: setuptools>=75.8.0
Requires-Dist: fusepy>=3.0.1
Requires-Dist: requests>=2.32.3
Requires-Dist: typing_extensions>=4.12.2
Provides-Extra: dev
Requires-Dist: pytest>=8.3.5; extra == "dev"
Requires-Dist: black>=23.12.1; extra == "dev"
Requires-Dist: mypy>=0.900; extra == "dev"
Requires-Dist: grpc-stubs>=1.53.0; extra == "dev"
Requires-Dist: pylint>=3.3.4; extra == "dev"
Requires-Dist: isort>=6.0.1; extra == "dev"
Dynamic: author
Dynamic: home-page
Dynamic: license-file
Dynamic: requires-python
